rvsearch/__init__.py
rvsearch/config.py
rvsearch/csv_handle.py
rvsearch/downloader.py
rvsearch/imagehash.py
rvsearch/main.py
rvsearch/raw_gui.py
rvsearch/run.py
rvsearch/rvsearch_gui.py
rvsearch/signals.py
rvsearch/video_utils.py
rvsearch-1.3.4.dist-info/LICENSE
rvsearch-1.3.4.dist-info/METADATA
rvsearch-1.3.4.dist-info/WHEEL
rvsearch-1.3.4.dist-info/entry_points.txt
rvsearch-1.3.4.dist-info/top_level.txt
rvsearch-1.3.4.dist-info/RECORD
