Metadata-Version: 2.1
Name: rvsearch
Version: 1.3.4
Summary: Tool to reverse search videos on YouTube based on frame similarities found
Home-page: http://pypi.org/project/rvsearch
Author: Sadiq SheshKhan
Author-email: sadiqush@gmail.com
License: GPLv3
Keywords: rvsearch,youtube,video,reverse_search
Platform: UNKNOWN
Requires-Python: >= 3
Requires-Dist: pandas
Requires-Dist: youtube-dl
Requires-Dist: opencv-python
Requires-Dist: numpy
Requires-Dist: setuptools
Requires-Dist: scikit-video
